MANIFEST.in
README.rst
requirements-test.txt
requirements.txt
setup.cfg
setup.py
src/nose_machineout/__init__.py
src/nose_machineout2.egg-info/PKG-INFO
src/nose_machineout2.egg-info/SOURCES.txt
src/nose_machineout2.egg-info/dependency_links.txt
src/nose_machineout2.egg-info/entry_points.txt
src/nose_machineout2.egg-info/top_level.txt
src/nose_machineout2.egg-info/zip-safe