Metadata-Version: 1.1
Name: nose-machineout2
Version: 0.5.1
Summary: Changes output of the nose testing tool into format easilyparsable by a machine.
Home-page: https://github.com/lambdalisue/nose_machineout2
Author: Alisue
Author-email: lambdalisue@hashnote.net
License: BSD
Download-URL: https://github.com/lambdalisue/nose_machineout2/tarball/master
Keywords: test unittest nose
Platform: UNKNOWN
Classifier: Development Status :: 4 - Beta
Classifier: Environment :: Console
Classifier: Intended Audience :: Developers
Classifier: License :: OSI Approved :: Python Software Foundation License
Classifier: Operating System :: POSIX
Classifier: Programming Language :: Python
Classifier: Programming Language :: Python :: 2
Classifier: Programming Language :: Python :: 2.6
Classifier: Programming Language :: Python :: 2.7
Classifier: Programming Language :: Python :: 3
Classifier: Programming Language :: Python :: 3.2
Classifier: Programming Language :: Python :: 3.3
Classifier: Programming Language :: Python :: 3.4
Classifier: Topic :: Software Development
